Metadata-Version: 2.1
Name: random-paaakg
Version: 0.0
Summary: deskrrr
Author-email: sonterkub@gmail.com
